romkan2/__init__.py
romkan2/_constants.py
romkan2/_generator.py
romkan2/common.py
romkan2/py.typed
romkan2/version.py
romkan2-0.1.1.dist-info/WHEEL
romkan2-0.1.1.dist-info/METADATA
romkan2-0.1.1.dist-info/RECORD
