Metadata-Version: 2.3
Name: romkan2
Version: 0.1.1
Summary: A Romaji/Kana conversion library
Keywords: japanese,romaji,kana
Author: Yasuhiro Yamaguchi, Mort Yao
Author-email: Yasuhiro Yamaguchi <me@altescy.jp>, Mort Yao <mort.yao@gmail.com>
License: BSD
Classifier: Development Status :: 4 - Beta
Classifier: Environment :: Console
Classifier: Intended Audience :: Developers
Classifier: Intended Audience :: Education
Classifier: Intended Audience :: Science/Research
Classifier: License :: OSI Approved :: BSD License
Classifier: Natural Language :: English
Classifier: Operating System :: OS Independent
Classifier: Programming Language :: Python
Classifier: Programming Language :: Python :: 3
Classifier: Programming Language :: Python :: 3.9
Classifier: Programming Language :: Python :: 3.10
Classifier: Programming Language :: Python :: 3.11
Classifier: Programming Language :: Python :: 3.12
Classifier: Programming Language :: Python :: 3.13
Classifier: Programming Language :: Python :: 3.14
Classifier: Topic :: Education
Classifier: Topic :: Text Processing :: Linguistic
Maintainer: Yasuhiro Yamaguchi
Maintainer-email: Yasuhiro Yamaguchi <me@altescy.jp>
Requires-Python: >=3.9
Project-URL: Homepage, https://github.com/altescy/romkan2
Project-URL: Issues, https://github.com/altescy/romkan2/issues
Project-URL: Repository, https://github.com/altescy/romkan2
